sigmaepsilon/__init__.py
sigmaepsilon/config.py
sigmaepsilon/core/__init__.py
sigmaepsilon/core/material.py
sigmaepsilon/examples/__init__.py
sigmaepsilon/examples/downloads.py
sigmaepsilon/examples/examples.py
sigmaepsilon/fem/__init__.py
sigmaepsilon/fem/constants.py
sigmaepsilon/fem/dofmap.py
sigmaepsilon/fem/ebc.py
sigmaepsilon/fem/femsolver.py
sigmaepsilon/fem/linemesh.py
sigmaepsilon/fem/mesh.py
sigmaepsilon/fem/metamesh.py
sigmaepsilon/fem/pointdata.py
sigmaepsilon/fem/structure.py
sigmaepsilon/fem/surfacemesh.py
sigmaepsilon/fem/cells/Q5V.py
sigmaepsilon/fem/cells/__init__.py
sigmaepsilon/fem/cells/andes.py
sigmaepsilon/fem/cells/bernoulli.py
sigmaepsilon/fem/cells/bernoulli2.py
sigmaepsilon/fem/cells/bernoulli3.py
sigmaepsilon/fem/cells/celldata.py
sigmaepsilon/fem/cells/cst.py
sigmaepsilon/fem/cells/elem.py
sigmaepsilon/fem/cells/h27.py
sigmaepsilon/fem/cells/h8.py
sigmaepsilon/fem/cells/lst.py
sigmaepsilon/fem/cells/meta.py
sigmaepsilon/fem/cells/q4.py
sigmaepsilon/fem/cells/q9.py
sigmaepsilon/fem/cells/tet10.py
sigmaepsilon/fem/cells/tet4.py
sigmaepsilon/fem/cells/wedge.py
sigmaepsilon/fem/cells/gen/__init__.py
sigmaepsilon/fem/cells/gen/b2.py
sigmaepsilon/fem/cells/gen/b3.py
sigmaepsilon/fem/homg/__init__.py
sigmaepsilon/fem/homg/ebc.py
sigmaepsilon/fem/homg/rve.py
sigmaepsilon/fem/homg/utils.py
sigmaepsilon/fem/material/__init__.py
sigmaepsilon/fem/material/beam.py
sigmaepsilon/fem/material/membrane.py
sigmaepsilon/fem/material/mindlinplate.py
sigmaepsilon/fem/material/mindlinshell.py
sigmaepsilon/fem/material/solid.py
sigmaepsilon/fem/material/solid3d.py
sigmaepsilon/fem/material/surface.py
sigmaepsilon/fourier/__init__.py
sigmaepsilon/fourier/beam.py
sigmaepsilon/fourier/loads.py
sigmaepsilon/fourier/plate.py
sigmaepsilon/fourier/postproc.py
sigmaepsilon/fourier/preproc.py
sigmaepsilon/fourier/problem.py
sigmaepsilon/fourier/proc.py
sigmaepsilon/fourier/utils.py
sigmaepsilon/material/__init__.py
sigmaepsilon/material/straintensor.py
sigmaepsilon-0.0.36.dist-info/LICENSE
sigmaepsilon-0.0.36.dist-info/METADATA
sigmaepsilon-0.0.36.dist-info/WHEEL
sigmaepsilon-0.0.36.dist-info/top_level.txt
sigmaepsilon-0.0.36.dist-info/RECORD
