Metadata-Version: 2.1
Name: sigmaepsilon
Version: 0.0.36
Summary: High-Performance Computational Mechanics in Python.
Home-page: https://github.com/dewloosh/sigmaepsilon
Download-URL: https://github.com/dewloosh/sigmaepsilon/archive/refs/tags/0.0.36.zip
Author: Bence Balogh
Author-email: benceeok@gmail.com
Classifier: Development Status :: 4 - Beta
Classifier: License :: Free for non-commercial use
Classifier: Programming Language :: Python :: 3.7
Classifier: Programming Language :: Python :: 3.8
Classifier: Programming Language :: Python :: 3.9
Classifier: Programming Language :: Python :: 3.10
Classifier: Programming Language :: Python :: 3 :: Only
Classifier: Operating System :: OS Independent
Classifier: Topic :: Scientific/Engineering
Classifier: Topic :: Scientific/Engineering :: Mathematics
Classifier: Topic :: Scientific/Engineering :: Physics
Requires-Python: >=3.6, <3.11
License-File: LICENSE
Requires-Dist: polymesh (>=0.0.25)
Requires-Dist: latexdocs (>=0.0.2)
